commoncrawlzain/__init__.py
commoncrawlzain/cc_index_export.py
commoncrawlzain/cc_index_word_count.py
commoncrawlzain/hostlinks_to_graph.py
commoncrawlzain/html_tag_count.py
commoncrawlzain/iana_tld.py
commoncrawlzain/linkmap2parquet.py
commoncrawlzain/main.py
commoncrawlzain/server_count.py
commoncrawlzain/server_ip_address.py
commoncrawlzain/sparkcc.py
commoncrawlzain/wat_extract_links.py
commoncrawlzain/word_count.py
commoncrawlzain-0.0.5.dist-info/LICENSE
commoncrawlzain-0.0.5.dist-info/METADATA
commoncrawlzain-0.0.5.dist-info/WHEEL
commoncrawlzain-0.0.5.dist-info/top_level.txt
commoncrawlzain-0.0.5.dist-info/RECORD
