Metadata-Version: 2.1
Name: commoncrawlzain
Version: 0.0.5
Summary: Extract email and contact information from commoncrawl index
Author-email: Zain Ulabidin <zainulabidin302@gmail.com>
Project-URL: Homepage, https://github.com/zainulabidin302/commoncrawl
Project-URL: Bug Tracker, https://github.com/zainulabidin302/commoncrawl/issues
Classifier: Programming Language :: Python :: 3
Classifier: License :: OSI Approved :: MIT License
Classifier: Operating System :: OS Independent
Requires-Python: >=3.7
License-File: LICENSE
